LICENSE
MANIFEST.in
README.md
setup.cfg
setup.py
pygbab/__init__.py
pygbab/babeltrace_lexer.py
pygments_babeltrace.egg-info/PKG-INFO
pygments_babeltrace.egg-info/SOURCES.txt
pygments_babeltrace.egg-info/dependency_links.txt
pygments_babeltrace.egg-info/entry_points.txt
pygments_babeltrace.egg-info/requires.txt
pygments_babeltrace.egg-info/top_level.txt