Metadata-Version: 1.0
Name: pygments-babeltrace
Version: 0.3.3
Summary: Pygments Babeltrace Lexer
Home-page: https://github.com/junousia/pygments-babeltrace
Author: Jukka Nousiainen
Author-email: jukka.nousiainen@gmail.com
License: UNKNOWN
Platform: UNKNOWN
